MANIFEST.in
README.md
pyproject.toml
setup.py
version
RandomX/CMakeLists.txt
RandomX.egg-info/PKG-INFO
RandomX.egg-info/SOURCES.txt
RandomX.egg-info/dependency_links.txt
RandomX.egg-info/top_level.txt
RandomX/build/CMakeCache.txt
RandomX/build/CMakeFiles/TargetDirectories.txt
RandomX/build/CMakeFiles/3.17.5/CompilerIdC/CMakeCCompilerId.c
RandomX/build/CMakeFiles/3.17.5/CompilerIdCXX/CMakeCXXCompilerId.cpp
RandomX/build/CMakeFiles/randomx-benchmark.dir/link.txt
RandomX/build/CMakeFiles/randomx-codegen.dir/link.txt
RandomX/build/CMakeFiles/randomx-tests.dir/link.txt
RandomX/build/CMakeFiles/randomx.dir/link.txt
RandomX/src/aes_hash.cpp
RandomX/src/aes_hash.hpp
RandomX/src/allocator.cpp
RandomX/src/allocator.hpp
RandomX/src/argon2.h
RandomX/src/argon2_avx2.c
RandomX/src/argon2_core.c
RandomX/src/argon2_core.h
RandomX/src/argon2_ref.c
RandomX/src/argon2_ssse3.c
RandomX/src/assembly_generator_x86.cpp
RandomX/src/assembly_generator_x86.hpp
RandomX/src/blake2_generator.cpp
RandomX/src/blake2_generator.hpp
RandomX/src/bytecode_machine.cpp
RandomX/src/bytecode_machine.hpp
RandomX/src/common.hpp
RandomX/src/configuration.h
RandomX/src/cpu.cpp
RandomX/src/cpu.hpp
RandomX/src/dataset.cpp
RandomX/src/dataset.hpp
RandomX/src/instruction.cpp
RandomX/src/instruction.hpp
RandomX/src/instruction_weights.hpp
RandomX/src/instructions_portable.cpp
RandomX/src/intrin_portable.h
RandomX/src/jit_compiler.hpp
RandomX/src/jit_compiler_a64.cpp
RandomX/src/jit_compiler_a64.hpp
RandomX/src/jit_compiler_a64_static.S
RandomX/src/jit_compiler_a64_static.hpp
RandomX/src/jit_compiler_fallback.hpp
RandomX/src/jit_compiler_x86.cpp
RandomX/src/jit_compiler_x86.hpp
RandomX/src/jit_compiler_x86_static.S
RandomX/src/jit_compiler_x86_static.hpp
RandomX/src/program.hpp
RandomX/src/randomx.cpp
RandomX/src/randomx.h
RandomX/src/reciprocal.c
RandomX/src/reciprocal.h
RandomX/src/soft_aes.cpp
RandomX/src/soft_aes.h
RandomX/src/superscalar.cpp
RandomX/src/superscalar.hpp
RandomX/src/superscalar_program.hpp
RandomX/src/virtual_machine.cpp
RandomX/src/virtual_machine.hpp
RandomX/src/virtual_memory.cpp
RandomX/src/virtual_memory.hpp
