Metadata-Version: 2.1
Name: RandomX
Version: 1.1.10.post3
Summary: RandomX Proof-of-Work Hasher
Home-page: https://github.com/xloem/RandomX-Python
License: UNKNOWN
Keywords: randomx,crypto,cryptocurrency,blockchain,pow
Platform: UNKNOWN
Classifier: Programming Language :: Python :: 3
Classifier: Operating System :: OS Independent
